source_faker/__init__.py
source_faker/airbyte_message_with_cached_json.py
source_faker/purchase_generator.py
source_faker/record_data/products.json
source_faker/run.py
source_faker/schemas/products.json
source_faker/schemas/purchases.json
source_faker/schemas/users.json
source_faker/source.py
source_faker/spec.json
source_faker/streams.py
source_faker/user_generator.py
source_faker/utils.py
airbyte_source_faker-6.2.38.dist-info/METADATA
airbyte_source_faker-6.2.38.dist-info/WHEEL
airbyte_source_faker-6.2.38.dist-info/entry_points.txt
airbyte_source_faker-6.2.38.dist-info/RECORD
