Metadata-Version: 2.1
Name: airbyte-source-faker
Version: 6.2.38
Summary: Source implementation for fake but realistic looking data.
Home-page: https://airbyte.com
License: ELv2
Author: Airbyte
Author-email: evan@airbyte.io
Requires-Python: >=3.10,<3.13
Classifier: License :: Other/Proprietary License
Classifier: Programming Language :: Python :: 3
Classifier: Programming Language :: Python :: 3.10
Classifier: Programming Language :: Python :: 3.11
Classifier: Programming Language :: Python :: 3.12
Requires-Dist: airbyte-cdk (>=6.61.6,<7.0)
Requires-Dist: mimesis (==6.1.1)
Project-URL: Documentation, https://docs.airbyte.com/integrations/sources/faker
Project-URL: Repository, https://github.com/airbytehq/airbyte
